cutplace/__init__.py
cutplace/_compat.py
cutplace/_tools.py
cutplace/applications.py
cutplace/checks.py
cutplace/data.py
cutplace/errors.py
cutplace/fields.py
cutplace/gui.py
cutplace/interface.py
cutplace/ranges.py
cutplace/rowio.py
cutplace/sql.py
cutplace/validio.py
cutplace-0.9.2.dist-info/AUTHORS.rst
cutplace-0.9.2.dist-info/LICENSE.txt
cutplace-0.9.2.dist-info/METADATA
cutplace-0.9.2.dist-info/WHEEL
cutplace-0.9.2.dist-info/entry_points.txt
cutplace-0.9.2.dist-info/RECORD
