Metadata-Version: 2.1
Name: cutplace
Version: 0.9.2
Summary: validate data stored in CSV, PRN, ODS or Excel files
Home-page: https://github.com/roskakori/cutplace
License: LGPL-3.0-only
Keywords: check,csv,excel,ods,validate
Author: Thomas Aglassinger
Author-email: roskakori@users.sourceforge.net
Requires-Python: >=3.9,<4
Classifier: Development Status :: 4 - Beta
Classifier: Environment :: Console
Classifier: Intended Audience :: Developers
Classifier: Intended Audience :: Information Technology
Classifier: License :: OSI Approved :: GNU Lesser General Public License v3 (LGPLv3)
Classifier: License :: OSI Approved :: GNU Library or Lesser General Public License (LGPL)
Classifier: Natural Language :: English
Classifier: Operating System :: OS Independent
Classifier: Programming Language :: Python
Classifier: Programming Language :: Python :: 3
Classifier: Programming Language :: Python :: 3.9
Classifier: Programming Language :: Python :: 3.10
Classifier: Programming Language :: Python :: 3.11
Classifier: Programming Language :: Python :: 3.12
Classifier: Programming Language :: Python :: 3.13
Classifier: Programming Language :: Python :: 3 :: Only
Classifier: Topic :: Documentation
Classifier: Topic :: Software Development :: Quality Assurance
Classifier: Topic :: Software Development :: Testing
Requires-Dist: XlsxWriter (>=3,<4)
Requires-Dist: xlrd (>=1.2,<2.0)
Project-URL: Changes, https://cutplace.readthedocs.io/en/latest/changes.html
Project-URL: Documentation, https://cutplace.readthedocs.io
Project-URL: Issue Tracker, https://github.com/roskakori/cutplace/issues
Project-URL: Repository, https://github.com/roskakori/cutplace.git
